{
  "spdxVersion": "SPDX-2.3",
  "dataLicense": "CC0-1.0",
  "SPDXID": "SPDXRef-DOCUMENT",
  "name": "libxr Dependency Manifest",
  "documentNamespace": "https://github.com/Jiu-xiao/libxr/spdx/b293208524b6ce6730c4d83297d6db2fff3e2ea3",
  "packages": [
    {
      "name": "libxr",
      "SPDXID": "SPDXRef-Package-Jiu-xiao-libxr",
      "versionInfo": "b293208524b6ce6730c4d83297d6db2fff3e2ea3",
      "downloadLocation": "git+https://github.com/Jiu-xiao/libxr.git@b293208524b6ce6730c4d83297d6db2fff3e2ea3",
      "filesAnalyzed": false
    },
    {
      "name": "linux",
      "SPDXID": "SPDXRef-Package-torvalds-linux",
      "versionInfo": "af4e9ef3d78420feb8fe58cd9a1ab80c501b3c08",
      "downloadLocation": "git+https://github.com/torvalds/linux.git@af4e9ef3d78420feb8fe58cd9a1ab80c501b3c08",
      "filesAnalyzed": false
    }
  ],
  "relationships": [
    {
      "spdxElementId": "SPDXRef-Package-Jiu-xiao-libxr",
      "relatedSpdxElement": "SPDXRef-Package-torvalds-linux",
      "relationshipType": "DEPENDS_ON"
    }
  ]
}